Workbook

Sheet Read Me
A1: Premier League Decision Engine — Results Workbook
A2: Calibrated match-outcome probabilities for the English Premier League, and a backtest of whether acting on them beats the bookmaker.
A4: Sheets
A5: Sheet | B5: Contents
A6: Summary | B6: Headline figures, the three ROI scenarios, and the selection levers.
A7: Model Metrics | B7: Walk-forward Brier / log loss / RPS / ECE, and the calibration gain.
A8: Edge Profile | B8: Return by relative-edge band. The core finding.
A9: Equity by Season | B9: Per-season bets, staked, profit and ROI.
A10: Bet Ledger | B10: All 2,154 placed bets, one row each. Pivot this.
A11: All Candidates | B11: Every EV+ opportunity considered, including those rejected.
A14: How to read the colours
A15: Black | B15: Live Excel formula over the raw sheets. Filter the data and it recalculates.
A16: Blue | B16: A hardcoded input, or a value carried from reports/results.json.
A17: Shaded | B17: The selected edge band, or the market baseline row.
A20: The one caveat that matters
A21: The headline +7.2% ROI uses a selection band chosen with hindsight over the whole sample. Refit that band on 2013/14–2018/19 and apply it blind to the following six seasons and ROI falls to +1.5%, with a 95% confidence interval that straddles zero. The honest reading is a marginal, unstable edge in a near-efficient market — not a money printer. Both numbers are on the Summary sheet.
A26: Provenance
A27: Source dataset | B27: epl_final.csv — 9,380 fixtures, 25 seasons (2000/01–2024/25)
A28: Odds | B28: football-data.co.uk closing odds, 99.1% coverage
A29: Evaluation | B29: Walk-forward: refit each season, predict the next, never look back
A30: Model | B30: XGBoost, uncalibrated (best Brier of the tree models)
A31: Bootstrap | B31: 10,000 resamples, clustered by season
A32: Reproduce | B32: python -m src.train && python -m src.backtest && python -m src.report
A33: Generated by | B33: python -m src.workbook

Sheet Summary
A1: Premier League Decision Engine — Results Summary
A2: Black figures are live Excel formulas over the Bet Ledger and All Candidates sheets. Blue figures are inputs or values carried from reports/results.json. Filter the raw sheets and the black figures recalculate.
A4: Headline — line-shopped, 12 held-out seasons
A5: Metric | B5: Value | C5: How it is computed
A6: Bets placed | B6: =COUNTA('Bet Ledger'!A2:A2155) -> 2154 | C6: Rows in Bet Ledger
A7: Hit rate | B7: =AVERAGE('Bet Ledger'!J2:J2155) -> 0.35701021 | C7: Mean of Won (1/0)
A8: Average odds | B8: =AVERAGE('Bet Ledger'!I2:I2155) -> 3.2208728 | C8: Mean decimal odds
A9: Flat-stake ROI | B9: =AVERAGE('Bet Ledger'!K2:K2155) -> 0.071717734 | C9: Mean unit return — ROI per £1 risked at constant stake
A10: Total staked (Kelly) | B10: =SUM('Bet Ledger'!L2:L2155) -> 131187.55 | C10: Sum of stakes, compounding
A11: Total profit (Kelly) | B11: =SUM('Bet Ledger'!M2:M2155) -> 6328.1122 | C11: Sum of profit
A12: ROI on turnover (Kelly) | B12: =SUM('Bet Ledger'!M2:M2155)/SUM('Bet Ledger'!L2:L2155) -> 0.04823714 | C12: Profit ÷ turnover
A13: Final bankroll | B13: ='Bet Ledger'!N2155 -> 7328.1122 | C13: Last row of Bankroll After
A15: The three ROI scenarios
A16: Only the first row is derived from this workbook's ledger. The other two come from reports/results.json and are shown in blue because nothing here recomputes them.
A17: Scenario | B17: Bets | C17: Flat ROI | D17: 95% CI low | E17: 95% CI high | F17: p(ROI≤0)
A18: Line-shopped, full period | B18: =COUNTA('Bet Ledger'!A2:A2155) -> 2154 | C18: =AVERAGE('Bet Ledger'!K2:K2155) -> 0.071717734 | D18: 0.013 | E18: 0.1338 | F18: 0.0074
A19: Single bookmaker | B19: 2166 | C19: 0.0324 | D19: -0.024 | E19: 0.0921 | F19: 0.1253
A20: Strict holdout | B20: 877 | C20: 0.0148 | D20: -0.0921 | E20: 0.127 | F20: 0.3792
A21: Read the holdout row before quoting the headline: refitting the selection band on 2013/14–2018/19 and applying it blind drops ROI to +1.5%, with a confidence interval straddling zero.
A24: Selection levers — pre-registered band
A25: Min absolute edge | B25: 0.03 | C25: Model probability must exceed the fair price by this margin
A26: Min relative edge | B26: 0.1 | C26: Below this the signal is noise (see Edge Profile)
A27: Max relative edge | B27: 0.4 | C27: Above this the model is overconfident on longshots
A28: Min decimal odds | B28: 1.8 | C28: Avoids heavy favourites where the vig dominates
A29: Max decimal odds | B29: 5 | C29: Caps longshot exposure
A30: Kelly fraction | B30: 0.25 | C30: Quarter-Kelly, to survive estimation error
A31: Max daily exposure | B31: 0.1 | C31: Cap on combined stake per matchday
A32: Starting bankroll | B32: 1000 | C32: Simulation start
A33: Candidates selected by these levers | B33: =COUNTIFS('All Candidates'!$N$2:$N$13528,"Yes") -> 2154 | C33: Reconciliation check: must equal the Bet Ledger row count in B6.
A35: Blue cells are inputs. Editing B25:B29 changes the Selected column on All Candidates, so you can test a different band against the same data. It does not re-run the Kelly simulation, whose stakes and bankroll are fixed at the band above. Note this is the pre-registered band used for the headline result — the strict-holdout row on this sheet uses a different, refitted band (min 10%, max 30%).
A38: Dataset
A39: Fixtures | B39: 9380
A40: Seasons | B40: 25
A41: Modellable after burn-in | B41: 8923
A42: Odds coverage | B42: 0.9912
A43: Candidate selections | B43: =COUNTA('All Candidates'!A2:A13528) -> 13527

Sheet Model Metrics
A1: Walk-forward model comparison
A2: 4,509 fixtures across 12 held-out seasons; the model is refit each season and never sees the season it predicts. Lower is better for Brier, log loss, RPS and ECE. Values are from reports/model_metrics.csv and shown in blue: this workbook does not re-run training.
A4: Model | B4: N | C4: Brier | D4: Log Loss | E4: RPS | F4: ECE | G4: Accuracy
A5: Market (de-vigged) | B5: 4509 | C5: 0.56335 | D5: 0.95267 | E5: 0.19412 | F5: 0.01045 | G5: 0.55689
A6: rf isotonic | B6: 4509 | C6: 0.57616 | D6: 0.98085 | E6: 0.19959 | F6: 0.00926 | G6: 0.54336
A7: xgb uncalibrated | B7: 4509 | C7: 0.57923 | D7: 0.9789 | E7: 0.20055 | F7: 0.01714 | G7: 0.5387
A8: xgb isotonic | B8: 4509 | C8: 0.58082 | D8: 0.97966 | E8: 0.20135 | F8: 0.01717 | G8: 0.53804
A9: xgb sigmoid | B9: 4509 | C9: 0.58163 | D9: 0.97909 | E9: 0.20206 | F9: 0.01708 | G9: 0.54003
A10: rf uncalibrated | B10: 4509 | C10: 0.59017 | D10: 0.99294 | E10: 0.20331 | F10: 0.02118 | G10: 0.51453
A13: What calibration bought
A14: Estimator | B14: Brier Before | C14: Brier After | D14: Brier Δ | E14: ECE Before | F14: ECE After | G14: ECE Δ
A15: random forest | B15: 0.59017 | C15: 0.57616 | D15: =IFERROR((C15-B15)/B15,0) -> -0.023738923 | E15: 0.02118 | F15: 0.00926 | G15: =IFERROR((F15-E15)/E15,0) -> -0.56279509
A16: xgboost | B16: 0.57923 | C16: 0.58082 | D16: =IFERROR((C16-B16)/B16,0) -> 0.0027450236 | E16: 0.01714 | F16: 0.01717 | G16: =IFERROR((F16-E16)/E16,0) -> 0.0017502917
A18: Isotonic regression cut Random Forest's calibration error by more than half. It did nothing for XGBoost, whose mlogloss objective is already a strictly proper scoring rule — so the model arrives calibrated and post-hoc fitting only adds noise. The Δ columns are formulas over the blue cells.

Sheet Edge Profile
A1: Realised return by relative edge
A2: Every cell is a COUNTIFS/SUMIFS over All Candidates — the whole candidate set, not just the bets that were placed. This is the finding the strategy is built on: returns are positive only in the middle bands.
A4: Edge Band | B4: Candidates | C4: Wins | D4: Hit Rate | E4: Avg Odds | F4: Flat ROI
A5: Below 0% | B5: =COUNTIFS('All Candidates'!$M$2:$M$13528,"Below 0%") -> 6889 | C5: =SUMIFS('All Candidates'!$K$2:$K$13528,'All Candidates'!$M$2:$M$13528,"Below 0%") -> 2333 | D5: =IFERROR(C5/B5,0) -> 0.33865583 | E5: =IFERROR(AVERAGEIFS('All Candidates'!$J$2:$J$13528,'All Candidates'!$M$2:$M$13528,"Below 0%"),0) -> 3.9244956 | F5: =IFERROR(AVERAGEIFS('All Candidates'!$L$2:$L$13528,'All Candidates'!$M$2:$M$13528,"Below 0%"),0) -> -0.013170271
A6: 0-5% | B6: =COUNTIFS('All Candidates'!$M$2:$M$13528,"0-5%") -> 1129 | C6: =SUMIFS('All Candidates'!$K$2:$K$13528,'All Candidates'!$M$2:$M$13528,"0-5%") -> 455 | D6: =IFERROR(C6/B6,0) -> 0.40301151 | E6: =IFERROR(AVERAGEIFS('All Candidates'!$J$2:$J$13528,'All Candidates'!$M$2:$M$13528,"0-5%"),0) -> 3.335093 | F6: =IFERROR(AVERAGEIFS('All Candidates'!$L$2:$L$13528,'All Candidates'!$M$2:$M$13528,"0-5%"),0) -> -0.035535872
A7: 5-10% | B7: =COUNTIFS('All Candidates'!$M$2:$M$13528,"5-10%") -> 1003 | C7: =SUMIFS('All Candidates'!$K$2:$K$13528,'All Candidates'!$M$2:$M$13528,"5-10%") -> 377 | D7: =IFERROR(C7/B7,0) -> 0.37587238 | E7: =IFERROR(AVERAGEIFS('All Candidates'!$J$2:$J$13528,'All Candidates'!$M$2:$M$13528,"5-10%"),0) -> 3.6090927 | F7: =IFERROR(AVERAGEIFS('All Candidates'!$L$2:$L$13528,'All Candidates'!$M$2:$M$13528,"5-10%"),0) -> -0.038454636
A8: 10-20% | B8: =COUNTIFS('All Candidates'!$M$2:$M$13528,"10-20%") -> 1581 | C8: =SUMIFS('All Candidates'!$K$2:$K$13528,'All Candidates'!$M$2:$M$13528,"10-20%") -> 599 | D8: =IFERROR(C8/B8,0) -> 0.37887413 | E8: =IFERROR(AVERAGEIFS('All Candidates'!$J$2:$J$13528,'All Candidates'!$M$2:$M$13528,"10-20%"),0) -> 3.7723846 | F8: =IFERROR(AVERAGEIFS('All Candidates'!$L$2:$L$13528,'All Candidates'!$M$2:$M$13528,"10-20%"),0) -> 0.10223276
A9: 20-40% | B9: =COUNTIFS('All Candidates'!$M$2:$M$13528,"20-40%") -> 1672 | C9: =SUMIFS('All Candidates'!$K$2:$K$13528,'All Candidates'!$M$2:$M$13528,"20-40%") -> 521 | D9: =IFERROR(C9/B9,0) -> 0.31160287 | E9: =IFERROR(AVERAGEIFS('All Candidates'!$J$2:$J$13528,'All Candidates'!$M$2:$M$13528,"20-40%"),0) -> 4.552494 | F9: =IFERROR(AVERAGEIFS('All Candidates'!$L$2:$L$13528,'All Candidates'!$M$2:$M$13528,"20-40%"),0) -> 0.025681818
A10: Above 40% | B10: =COUNTIFS('All Candidates'!$M$2:$M$13528,"Above 40%") -> 1253 | C10: =SUMIFS('All Candidates'!$K$2:$K$13528,'All Candidates'!$M$2:$M$13528,"Above 40%") -> 224 | D10: =IFERROR(C10/B10,0) -> 0.17877095 | E10: =IFERROR(AVERAGEIFS('All Candidates'!$J$2:$J$13528,'All Candidates'!$M$2:$M$13528,"Above 40%"),0) -> 7.9061053 | F10: =IFERROR(AVERAGEIFS('All Candidates'!$L$2:$L$13528,'All Candidates'!$M$2:$M$13528,"Above 40%"),0) -> -0.047438148
A11: Total | B11: =SUM(B5:B10) -> 13527 | C11: =SUM(C5:C10) -> 4509
A13: Shaded rows are the selected band. Bands are cut at 0/5/10/20/40% relative edge by the Edge Band formula in All Candidates column M; edit that formula to re-cut them.

Sheet Equity by Season
A1: Bankroll progression by season
A2: SUMIFS over the Bet Ledger by season. Six of twelve seasons lose money — the edge is real but far from monotonic.
A4: Season | B4: Bets | C4: Hit Rate | D4: Staked (£) | E4: Profit (£) | F4: Season ROI | G4: Cumulative Profit (£)
A5: 2013/14 | B5: =COUNTIFS('Bet Ledger'!$A$2:$A$2155,"2013/14") -> 157 | C5: =IFERROR(AVERAGEIFS('Bet Ledger'!$J$2:$J$2155,'Bet Ledger'!$A$2:$A$2155,"2013/14"),0) -> 0.37579618 | D5: =SUMIFS('Bet Ledger'!$L$2:$L$2155,'Bet Ledger'!$A$2:$A$2155,"2013/14") -> 3388.9048 | E5: =SUMIFS('Bet Ledger'!$M$2:$M$2155,'Bet Ledger'!$A$2:$A$2155,"2013/14") -> 154.42965 | F5: =IFERROR(E5/D5,0) -> 0.045569191 | G5: =SUM($E$5:E5) -> 154.42965
A6: 2014/15 | B6: =COUNTIFS('Bet Ledger'!$A$2:$A$2155,"2014/15") -> 193 | C6: =IFERROR(AVERAGEIFS('Bet Ledger'!$J$2:$J$2155,'Bet Ledger'!$A$2:$A$2155,"2014/15"),0) -> 0.36787565 | D6: =SUMIFS('Bet Ledger'!$L$2:$L$2155,'Bet Ledger'!$A$2:$A$2155,"2014/15") -> 3830.6812 | E6: =SUMIFS('Bet Ledger'!$M$2:$M$2155,'Bet Ledger'!$A$2:$A$2155,"2014/15") -> -106.91519 | F6: =IFERROR(E6/D6,0) -> -0.027910228 | G6: =SUM($E$5:E6) -> 47.514466
A7: 2015/16 | B7: =COUNTIFS('Bet Ledger'!$A$2:$A$2155,"2015/16") -> 193 | C7: =IFERROR(AVERAGEIFS('Bet Ledger'!$J$2:$J$2155,'Bet Ledger'!$A$2:$A$2155,"2015/16"),0) -> 0.39378238 | D7: =SUMIFS('Bet Ledger'!$L$2:$L$2155,'Bet Ledger'!$A$2:$A$2155,"2015/16") -> 3922.5538 | E7: =SUMIFS('Bet Ledger'!$M$2:$M$2155,'Bet Ledger'!$A$2:$A$2155,"2015/16") -> 342.71554 | F7: =IFERROR(E7/D7,0) -> 0.087370515 | G7: =SUM($E$5:E7) -> 390.23001
A8: 2016/17 | B8: =COUNTIFS('Bet Ledger'!$A$2:$A$2155,"2016/17") -> 174 | C8: =IFERROR(AVERAGEIFS('Bet Ledger'!$J$2:$J$2155,'Bet Ledger'!$A$2:$A$2155,"2016/17"),0) -> 0.32183908 | D8: =SUMIFS('Bet Ledger'!$L$2:$L$2155,'Bet Ledger'!$A$2:$A$2155,"2016/17") -> 4194.8149 | E8: =SUMIFS('Bet Ledger'!$M$2:$M$2155,'Bet Ledger'!$A$2:$A$2155,"2016/17") -> -212.90656 | F8: =IFERROR(E8/D8,0) -> -0.050754696 | G8: =SUM($E$5:E8) -> 177.32345
A9: 2017/18 | B9: =COUNTIFS('Bet Ledger'!$A$2:$A$2155,"2017/18") -> 163 | C9: =IFERROR(AVERAGEIFS('Bet Ledger'!$J$2:$J$2155,'Bet Ledger'!$A$2:$A$2155,"2017/18"),0) -> 0.41717791 | D9: =SUMIFS('Bet Ledger'!$L$2:$L$2155,'Bet Ledger'!$A$2:$A$2155,"2017/18") -> 5247.9795 | E9: =SUMIFS('Bet Ledger'!$M$2:$M$2155,'Bet Ledger'!$A$2:$A$2155,"2017/18") -> 952.79888 | F9: =IFERROR(E9/D9,0) -> 0.18155537 | G9: =SUM($E$5:E9) -> 1130.1223
A10: 2018/19 | B10: =COUNTIFS('Bet Ledger'!$A$2:$A$2155,"2018/19") -> 179 | C10: =IFERROR(AVERAGEIFS('Bet Ledger'!$J$2:$J$2155,'Bet Ledger'!$A$2:$A$2155,"2018/19"),0) -> 0.34078212 | D10: =SUMIFS('Bet Ledger'!$L$2:$L$2155,'Bet Ledger'!$A$2:$A$2155,"2018/19") -> 7063.6704 | E10: =SUMIFS('Bet Ledger'!$M$2:$M$2155,'Bet Ledger'!$A$2:$A$2155,"2018/19") -> -49.124422 | F10: =IFERROR(E10/D10,0) -> -0.0069545179 | G10: =SUM($E$5:E10) -> 1080.9979
A11: 2019/20 | B11: =COUNTIFS('Bet Ledger'!$A$2:$A$2155,"2019/20") -> 178 | C11: =IFERROR(AVERAGEIFS('Bet Ledger'!$J$2:$J$2155,'Bet Ledger'!$A$2:$A$2155,"2019/20"),0) -> 0.35393258 | D11: =SUMIFS('Bet Ledger'!$L$2:$L$2155,'Bet Ledger'!$A$2:$A$2155,"2019/20") -> 7037.1138 | E11: =SUMIFS('Bet Ledger'!$M$2:$M$2155,'Bet Ledger'!$A$2:$A$2155,"2019/20") -> 979.37709 | F11: =IFERROR(E11/D11,0) -> 0.13917312 | G11: =SUM($E$5:E11) -> 2060.375
A12: 2020/21 | B12: =COUNTIFS('Bet Ledger'!$A$2:$A$2155,"2020/21") -> 192 | C12: =IFERROR(AVERAGEIFS('Bet Ledger'!$J$2:$J$2155,'Bet Ledger'!$A$2:$A$2155,"2020/21"),0) -> 0.375 | D12: =SUMIFS('Bet Ledger'!$L$2:$L$2155,'Bet Ledger'!$A$2:$A$2155,"2020/21") -> 16319.787 | E12: =SUMIFS('Bet Ledger'!$M$2:$M$2155,'Bet Ledger'!$A$2:$A$2155,"2020/21") -> 3131.1227 | F12: =IFERROR(E12/D12,0) -> 0.19186051 | G12: =SUM($E$5:E12) -> 5191.4977
A13: 2021/22 | B13: =COUNTIFS('Bet Ledger'!$A$2:$A$2155,"2021/22") -> 184 | C13: =IFERROR(AVERAGEIFS('Bet Ledger'!$J$2:$J$2155,'Bet Ledger'!$A$2:$A$2155,"2021/22"),0) -> 0.29891304 | D13: =SUMIFS('Bet Ledger'!$L$2:$L$2155,'Bet Ledger'!$A$2:$A$2155,"2021/22") -> 16520.789 | E13: =SUMIFS('Bet Ledger'!$M$2:$M$2155,'Bet Ledger'!$A$2:$A$2155,"2021/22") -> -1847.3731 | F13: =IFERROR(E13/D13,0) -> -0.11182112 | G13: =SUM($E$5:E13) -> 3344.1246
A14: 2022/23 | B14: =COUNTIFS('Bet Ledger'!$A$2:$A$2155,"2022/23") -> 173 | C14: =IFERROR(AVERAGEIFS('Bet Ledger'!$J$2:$J$2155,'Bet Ledger'!$A$2:$A$2155,"2022/23"),0) -> 0.38728324 | D14: =SUMIFS('Bet Ledger'!$L$2:$L$2155,'Bet Ledger'!$A$2:$A$2155,"2022/23") -> 21952.266 | E14: =SUMIFS('Bet Ledger'!$M$2:$M$2155,'Bet Ledger'!$A$2:$A$2155,"2022/23") -> 3159.8227 | F14: =IFERROR(E14/D14,0) -> 0.14394062 | G14: =SUM($E$5:E14) -> 6503.9473
A15: 2023/24 | B15: =COUNTIFS('Bet Ledger'!$A$2:$A$2155,"2023/24") -> 193 | C15: =IFERROR(AVERAGEIFS('Bet Ledger'!$J$2:$J$2155,'Bet Ledger'!$A$2:$A$2155,"2023/24"),0) -> 0.31606218 | D15: =SUMIFS('Bet Ledger'!$L$2:$L$2155,'Bet Ledger'!$A$2:$A$2155,"2023/24") -> 21226.267 | E15: =SUMIFS('Bet Ledger'!$M$2:$M$2155,'Bet Ledger'!$A$2:$A$2155,"2023/24") -> -1051.0765 | F15: =IFERROR(E15/D15,0) -> -0.049517728 | G15: =SUM($E$5:E15) -> 5452.8708
A16: 2024/25 | B16: =COUNTIFS('Bet Ledger'!$A$2:$A$2155,"2024/25") -> 175 | C16: =IFERROR(AVERAGEIFS('Bet Ledger'!$J$2:$J$2155,'Bet Ledger'!$A$2:$A$2155,"2024/25"),0) -> 0.34285714 | D16: =SUMIFS('Bet Ledger'!$L$2:$L$2155,'Bet Ledger'!$A$2:$A$2155,"2024/25") -> 20482.724 | E16: =SUMIFS('Bet Ledger'!$M$2:$M$2155,'Bet Ledger'!$A$2:$A$2155,"2024/25") -> 875.2414 | F16: =IFERROR(E16/D16,0) -> 0.042730714 | G16: =SUM($E$5:E16) -> 6328.1122
A17: Total | B17: =SUM(B5:B16) -> 2154 | D17: =SUM(D5:D16) -> 131187.55 | E17: =SUM(E5:E16) -> 6328.1122 | F17: =IFERROR(E17/D17,0) -> 0.04823714

Sheet Bet Ledger
A1: Season | B1: Match Date | C1: Home Team | D1: Away Team | E1: Selection | F1: Model Prob | G1: Market Fair Prob | H1: Relative Edge | I1: Decimal Odds | J1: Won | K1: Unit Return | L1: Stake (£) | M1: Profit (£) | N1: Bankroll After (£) | O1: Edge Band
A2: 2013/14 | B2: 41503 | C2: Norwich | D2: Everton | E2: Draw | F2: 0.37172213 | G2: 0.29080387 | H2: 0.27825717 | I2: 3.41 | J2: 1 | K2: 2.41 | L2: 20 | M2: 48.2 | N2: 1048.2 | O2: =IF(H2<=0,"Below 0%",IF(H2<=0.05,"0-5%",IF(H2<=0.1,"5-10%",IF(H2<=0.2,"10-20%",IF(H2<=0.4,"20-40%","Above 40%"))))) -> 20-40%
A3: 2013/14 | B3: 41503 | C3: Swansea | D3: Man United | E3: Away | F3: 0.61875421 | G3: 0.48348376 | H3: 0.27978281 | I3: 2.1 | J3: 1 | K3: 1.1 | L3: 20 | M3: 22 | N3: 1070.2 | O3: =IF(H3<=0,"Below 0%",IF(H3<=0.05,"0-5%",IF(H3<=0.1,"5-10%",IF(H3<=0.2,"10-20%",IF(H3<=0.4,"20-40%","Above 40%"))))) -> 20-40%
A4: 2013/14 | B4: 41503 | C4: West Brom | D4: Southampton | E4: Draw | F4: 0.35499758 | G4: 0.288583 | H4: 0.23014031 | I4: 3.45 | J4: 0 | K4: -1 | L4: 20 | M4: -20 | N4: 1050.2 | O4: =IF(H4<=0,"Below 0%",IF(H4<=0.05,"0-5%",IF(H4<=0.1,"5-10%",IF(H4<=0.2,"10-20%",IF(H4<=0.4,"20-40%","Above 40%"))))) -> 20-40%
A5: 2013/14 | B5: 41504 | C5: Crystal Palace | D5: Tottenham | E5: Draw | F5: 0.33827412 | G5: 0.25675586 | H5: 0.31749331 | I5: 3.95 | J5: 0 | K5: -1 | L5: 21.004 | M5: -21.004 | N5: 1029.196 | O5: =IF(H5<=0,"Below 0%",IF(H5<=0.05,"0-5%",IF(H5<=0.1,"5-10%",IF(H5<=0.2,"10-20%",IF(H5<=0.4,"20-40%","Above 40%"))))) -> 20-40%
A6: 2013/14 | B6: 41510 | C6: Aston Villa | D6: Liverpool | E6: Draw | F6: 0.3328557 | G6: 0.26130778 | H6: 0.27380707 | I6: 3.83 | J6: 0 | K6: -1 | L6: 19.196096 | M6: -19.196096 | N6: 1009.9999 | O6: =IF(H6<=0,"Below 0%",IF(H6<=0.05,"0-5%",IF(H6<=0.1,"5-10%",IF(H6<=0.2,"10-20%",IF(H6<=0.4,"20-40%","Above 40%"))))) -> 20-40%
A7: 2013/14 | B7: 41510 | C7: Everton | D7: West Brom | E7: Draw | F7: 0.28755397 | G7: 0.23087085 | H7: 0.24551874 | I7: 4.35 | J7: 1 | K7: 3.35 | L7: 17.968387 | M7: 60.194098 | N7: 1070.194 | O7: =IF(H7<=0,"Below 0%",IF(H7<=0.05,"0-5%",IF(H7<=0.1,"5-10%",IF(H7<=0.2,"10-20%",IF(H7<=0.4,"20-40%","Above 40%"))))) -> 20-40%
A8: 2013/14 | B8: 41510 | C8: Fulham | D8: Arsenal | E8: Away | F8: 0.52229393 | G8: 0.46160632 | H8: 0.13147047 | I8: 2.15 | J8: 1 | K8: 1.15 | L8: 19.196096 | M8: 22.07551 | N8: 1092.2695 | O8: =IF(H8<=0,"Below 0%",IF(H8<=0.05,"0-5%",IF(H8<=0.1,"5-10%",IF(H8<=0.2,"10-20%",IF(H8<=0.4,"20-40%","Above 40%"))))) -> 10-20%
A9: 2013/14 | B9: 41510 | C9: Hull | D9: Norwich | E9: Home | F9: 0.47866964 | G9: 0.40224535 | H9: 0.18999421 | I9: 2.5 | J9: 1 | K9: 1.5 | L9: 19.196096 | M9: 28.794144 | N9: 1121.0637 | O9: =IF(H9<=0,"Below 0%",IF(H9<=0.05,"0-5%",IF(H9<=0.1,"5-10%",IF(H9<=0.2,"10-20%",IF(H9<=0.4,"20-40%","Above 40%"))))) -> 10-20%
A10: 2013/14 | B10: 41510 | C10: Newcastle | D10: West Ham | E10: Draw | F10: 0.34644055 | G10: 0.29211889 | H10: 0.18595738 | I10: 3.4 | J10: 1 | K10: 2.4 | L10: 17.786171 | M10: 42.68681 | N10: 1163.7505 | O10: =IF(H10<=0,"Below 0%",IF(H10<=0.05,"0-5%",IF(H10<=0.1,"5-10%",IF(H10<=0.2,"10-20%",IF(H10<=0.4,"20-40%","Above 40%"))))) -> 10-20%
A11: 2013/14 | B11: 41510 | C11: Newcastle | D11: West Ham | E11: Away | F11: 0.31035879 | G11: 0.27977584 | H11: 0.10931235 | I11: 3.55 | J11: 0 | K11: -1 | L11: 9.5767546 | M11: -9.5767546 | N11: 1154.1737 | O11: =IF(H11<=0,"Below 0%",IF(H11<=0.05,"0-5%",IF(H11<=0.1,"5-10%",IF(H11<=0.2,"10-20%",IF(H11<=0.4,"20-40%","Above 40%"))))) -> 10-20%
A12: 2013/14 | B12: 41512 | C12: Man United | D12: Chelsea | E12: Home | F12: 0.54497409 | G12: 0.4010426 | H12: 0.35889328 | I12: 2.5 | J12: 0 | K12: -1 | L12: 23.083474 | M12: -23.083474 | N12: 1131.0902 | O12: =IF(H12<=0,"Below 0%",IF(H12<=0.05,"0-5%",IF(H12<=0.1,"5-10%",IF(H12<=0.2,"10-20%",IF(H12<=0.4,"20-40%","Above 40%"))))) -> 20-40%
A13: 2013/14 | B13: 41517 | C13: Crystal Palace | D13: Sunderland | E13: Draw | F13: 0.3398405 | G13: 0.29681458 | H13: 0.14495891 | I13: 3.35 | J13: 0 | K13: -1 | L13: 16.661402 | M13: -16.661402 | N13: 1114.4288 | O13: =IF(H13<=0,"Below 0%",IF(H13<=0.05,"0-5%",IF(H13<=0.1,"5-10%",IF(H13<=0.2,"10-20%",IF(H13<=0.4,"20-40%","Above 40%"))))) -> 10-20%
... A2155: 2024/25 | B2155: 45782 | C2155: Crystal Palace | D2155: Nott'm Forest | E2155: Away | F2155: 0.36651084 | G2155: 0.30189217 | H2155: 0.21404552 | I2155: 3.24 | J2155: 0 | K2155: -1 | L2155: 149.55331 | M2155: -149.55331 | N2155: 7328.1122 | O2155: =IF(H2155<=0,"Below 0%",IF(H2155<=0.05,"0-5%",IF(H2155<=0.1,"5-10%",IF(H2155<=0.2,"10-20%",IF(H2155<=0.4,"20-40%","Above 40%"))))) -> 20-40%

Sheet All Candidates
A1: Season | B1: Match Date | C1: Home Team | D1: Away Team | E1: Selection | F1: Model Prob | G1: Market Fair Prob | H1: Abs Edge | I1: Relative Edge | J1: Decimal Odds | K1: Won | L1: Unit Return | M1: Edge Band | N1: Selected
A2: 2013/14 | B2: 41503 | C2: Arsenal | D2: Aston Villa | E2: Home | F2: 0.59197068 | G2: 0.70156893 | H2: -0.10959825 | I2: -0.15621879 | J2: 1.44 | K2: 0 | L2: -1 | M2: =IF(I2<=0,"Below 0%",IF(I2<=0.05,"0-5%",IF(I2<=0.1,"5-10%",IF(I2<=0.2,"10-20%",IF(I2<=0.4,"20-40%","Above 40%"))))) -> Below 0% | N2: =IF(AND(H2>=Summary!$B$25,I2>=Summary!$B$26,I2<=Summary!$B$27,J2>=Summary!$B$28,J2<=Summary!$B$29,F2*J2>1),"Yes","No") -> No
A3: 2013/14 | B3: 41503 | C3: Arsenal | D3: Aston Villa | E3: Draw | F3: 0.32194293 | G3: 0.19428063 | H3: 0.1276623 | I3: 0.65710256 | J3: 5.2 | K3: 0 | L3: -1 | M3: =IF(I3<=0,"Below 0%",IF(I3<=0.05,"0-5%",IF(I3<=0.1,"5-10%",IF(I3<=0.2,"10-20%",IF(I3<=0.4,"20-40%","Above 40%"))))) -> Above 40% | N3: =IF(AND(H3>=Summary!$B$25,I3>=Summary!$B$26,I3<=Summary!$B$27,J3>=Summary!$B$28,J3<=Summary!$B$29,F3*J3>1),"Yes","No") -> No
A4: 2013/14 | B4: 41503 | C4: Arsenal | D4: Aston Villa | E4: Away | F4: 0.086086422 | G4: 0.10415044 | H4: -0.018064017 | I4: -0.17344159 | J4: 9.7 | K4: 1 | L4: 8.7 | M4: =IF(I4<=0,"Below 0%",IF(I4<=0.05,"0-5%",IF(I4<=0.1,"5-10%",IF(I4<=0.2,"10-20%",IF(I4<=0.4,"20-40%","Above 40%"))))) -> Below 0% | N4: =IF(AND(H4>=Summary!$B$25,I4>=Summary!$B$26,I4<=Summary!$B$27,J4>=Summary!$B$28,J4<=Summary!$B$29,F4*J4>1),"Yes","No") -> No
A5: 2013/14 | B5: 41503 | C5: Liverpool | D5: Stoke | E5: Home | F5: 0.84738171 | G5: 0.69690826 | H5: 0.15047345 | I5: 0.21591572 | J5: 1.44 | K5: 1 | L5: 0.44 | M5: =IF(I5<=0,"Below 0%",IF(I5<=0.05,"0-5%",IF(I5<=0.1,"5-10%",IF(I5<=0.2,"10-20%",IF(I5<=0.4,"20-40%","Above 40%"))))) -> 20-40% | N5: =IF(AND(H5>=Summary!$B$25,I5>=Summary!$B$26,I5<=Summary!$B$27,J5>=Summary!$B$28,J5<=Summary!$B$29,F5*J5>1),"Yes","No") -> No
A6: 2013/14 | B6: 41503 | C6: Liverpool | D6: Stoke | E6: Draw | F6: 0.098968364 | G6: 0.20273695 | H6: -0.10376858 | I6: -0.51183854 | J6: 4.95 | K6: 0 | L6: -1 | M6: =IF(I6<=0,"Below 0%",IF(I6<=0.05,"0-5%",IF(I6<=0.1,"5-10%",IF(I6<=0.2,"10-20%",IF(I6<=0.4,"20-40%","Above 40%"))))) -> Below 0% | N6: =IF(AND(H6>=Summary!$B$25,I6>=Summary!$B$26,I6<=Summary!$B$27,J6>=Summary!$B$28,J6<=Summary!$B$29,F6*J6>1),"Yes","No") -> No
A7: 2013/14 | B7: 41503 | C7: Liverpool | D7: Stoke | E7: Away | F7: 0.053649876 | G7: 0.10035479 | H7: -0.046704913 | I7: -0.46539795 | J7: 10 | K7: 0 | L7: -1 | M7: =IF(I7<=0,"Below 0%",IF(I7<=0.05,"0-5%",IF(I7<=0.1,"5-10%",IF(I7<=0.2,"10-20%",IF(I7<=0.4,"20-40%","Above 40%"))))) -> Below 0% | N7: =IF(AND(H7>=Summary!$B$25,I7>=Summary!$B$26,I7<=Summary!$B$27,J7>=Summary!$B$28,J7<=Summary!$B$29,F7*J7>1),"Yes","No") -> No
A8: 2013/14 | B8: 41503 | C8: Norwich | D8: Everton | E8: Home | F8: 0.25153905 | G8: 0.2960123 | H8: -0.044473246 | I8: -0.15024121 | J8: 3.35 | K8: 0 | L8: -1 | M8: =IF(I8<=0,"Below 0%",IF(I8<=0.05,"0-5%",IF(I8<=0.1,"5-10%",IF(I8<=0.2,"10-20%",IF(I8<=0.4,"20-40%","Above 40%"))))) -> Below 0% | N8: =IF(AND(H8>=Summary!$B$25,I8>=Summary!$B$26,I8<=Summary!$B$27,J8>=Summary!$B$28,J8<=Summary!$B$29,F8*J8>1),"Yes","No") -> No
A9: 2013/14 | B9: 41503 | C9: Norwich | D9: Everton | E9: Draw | F9: 0.37172213 | G9: 0.29080387 | H9: 0.080918262 | I9: 0.27825717 | J9: 3.41 | K9: 1 | L9: 2.41 | M9: =IF(I9<=0,"Below 0%",IF(I9<=0.05,"0-5%",IF(I9<=0.1,"5-10%",IF(I9<=0.2,"10-20%",IF(I9<=0.4,"20-40%","Above 40%"))))) -> 20-40% | N9: =IF(AND(H9>=Summary!$B$25,I9>=Summary!$B$26,I9<=Summary!$B$27,J9>=Summary!$B$28,J9<=Summary!$B$29,F9*J9>1),"Yes","No") -> Yes
A10: 2013/14 | B10: 41503 | C10: Norwich | D10: Everton | E10: Away | F10: 0.37673882 | G10: 0.41318383 | H10: -0.036445016 | I10: -0.088205329 | J10: 2.4 | K10: 0 | L10: -1 | M10: =IF(I10<=0,"Below 0%",IF(I10<=0.05,"0-5%",IF(I10<=0.1,"5-10%",IF(I10<=0.2,"10-20%",IF(I10<=0.4,"20-40%","Above 40%"))))) -> Below 0% | N10: =IF(AND(H10>=Summary!$B$25,I10>=Summary!$B$26,I10<=Summary!$B$27,J10>=Summary!$B$28,J10<=Summary!$B$29,F10*J10>1),"Yes","No") -> No
A11: 2013/14 | B11: 41503 | C11: Sunderland | D11: Fulham | E11: Home | F11: 0.35391018 | G11: 0.43306452 | H11: -0.079154338 | I11: -0.18277724 | J11: 2.3 | K11: 0 | L11: -1 | M11: =IF(I11<=0,"Below 0%",IF(I11<=0.05,"0-5%",IF(I11<=0.1,"5-10%",IF(I11<=0.2,"10-20%",IF(I11<=0.4,"20-40%","Above 40%"))))) -> Below 0% | N11: =IF(AND(H11>=Summary!$B$25,I11>=Summary!$B$26,I11<=Summary!$B$27,J11>=Summary!$B$28,J11<=Summary!$B$29,F11*J11>1),"Yes","No") -> No
A12: 2013/14 | B12: 41503 | C12: Sunderland | D12: Fulham | E12: Draw | F12: 0.25264016 | G12: 0.28870968 | H12: -0.036069519 | I12: -0.12493353 | J12: 3.45 | K12: 0 | L12: -1 | M12: =IF(I12<=0,"Below 0%",IF(I12<=0.05,"0-5%",IF(I12<=0.1,"5-10%",IF(I12<=0.2,"10-20%",IF(I12<=0.4,"20-40%","Above 40%"))))) -> Below 0% | N12: =IF(AND(H12>=Summary!$B$25,I12>=Summary!$B$26,I12<=Summary!$B$27,J12>=Summary!$B$28,J12<=Summary!$B$29,F12*J12>1),"Yes","No") -> No
A13: 2013/14 | B13: 41503 | C13: Sunderland | D13: Fulham | E13: Away | F13: 0.39344963 | G13: 0.27822581 | H13: 0.11522383 | I13: 0.41413782 | J13: 3.58 | K13: 1 | L13: 2.58 | M13: =IF(I13<=0,"Below 0%",IF(I13<=0.05,"0-5%",IF(I13<=0.1,"5-10%",IF(I13<=0.2,"10-20%",IF(I13<=0.4,"20-40%","Above 40%"))))) -> Above 40% | N13: =IF(AND(H13>=Summary!$B$25,I13>=Summary!$B$26,I13<=Summary!$B$27,J13>=Summary!$B$28,J13<=Summary!$B$29,F13*J13>1),"Yes","No") -> No
... A13528: 2024/25 | B13528: 45782 | C13528: Crystal Palace | D13528: Nott'm Forest | E13528: Away | F13528: 0.36651084 | G13528: 0.30189217 | H13528: 0.064618667 | I13528: 0.21404552 | J13528: 3.24 | K13528: 0 | L13528: -1 | M13528: =IF(I13528<=0,"Below 0%",IF(I13528<=0.05,"0-5%",IF(I13528<=0.1,"5-10%",IF(I13528<=0.2,"10-20%",IF(I13528<=0.4,"20-40%","Above 40%"))))) -> 20-40% | N13528: =IF(AND(H13528>=Summary!$B$25,I13528>=Summary!$B$26,I13528<=Summary!$B$27,J13528>=Summary!$B$28,J13528<=Summary!$B$29,F13528*J13528>1),"Yes","No") -> Yes
